README.md
setup.cfg
setup.py
example/__init__.py
example/example.py
mapser/__init__.py
mapser/mapser.py
mapser.egg-info/PKG-INFO
mapser.egg-info/SOURCES.txt
mapser.egg-info/dependency_links.txt
mapser.egg-info/top_level.txt