Metadata-Version: 1.1
Name: mapser
Version: 0.2.0
Summary: Generated map file analyzer
Home-page: https://gitlab.com/kazbeel/mapser
Author: kazbeel
Author-email: woozycoder@gmail.com
License: MIT
Keywords: embedded arm cortex-m map-file analyzer
Platform: UNKNOWN
Classifier: Development Status :: 4 - Beta
Classifier: Environment :: Console
Classifier: Intended Audience :: Developers
Classifier: License :: OSI Approved :: MIT License
Classifier: Operating System :: OS Independent
Classifier: Programming Language :: Python
Classifier: Programming Language :: Python :: 2
Classifier: Programming Language :: Python :: 2.7
Classifier: Programming Language :: Python :: 3
Classifier: Programming Language :: Python :: 3.6
Classifier: Programming Language :: Python :: Implementation
Classifier: Programming Language :: Python :: Implementation :: CPython
Classifier: Programming Language :: Python :: Implementation :: PyPy
Classifier: Topic :: Software Development
